livedoorblog/__init__.py
livedoorblog/livedoorblog.py
livedoorblog-0.0.3.dist-info/LICENSE
livedoorblog-0.0.3.dist-info/METADATA
livedoorblog-0.0.3.dist-info/WHEEL
livedoorblog-0.0.3.dist-info/top_level.txt
livedoorblog-0.0.3.dist-info/RECORD
