Metadata-Version: 2.1
Name: livedoorblog
Version: 0.0.3
Summary: Livedoor Blog API Client for Python
Home-page: https://github.com/matz1ppei/livedoorblog
Author: Ippei Matsubara
Author-email: matz1ppei@gmail.com
License: UNKNOWN
Platform: UNKNOWN
Classifier: Programming Language :: Python :: 3
Classifier: License :: OSI Approved :: MIT License
Requires-Dist: requests
